README.rst
setup.py
jw/__init__.py
jw.ui.tk.egg-info/PKG-INFO
jw.ui.tk.egg-info/SOURCES.txt
jw.ui.tk.egg-info/dependency_links.txt
jw.ui.tk.egg-info/entry_points.txt
jw.ui.tk.egg-info/requires.txt
jw.ui.tk.egg-info/top_level.txt
jw/ui/__init__.py
jw/ui/tk/__init__.py