Metadata-Version: 1.1
Name: jw.ui.tk
Version: 0.1.1
Summary: Tk User Interface
Home-page: https://pypi.python.org/pypi/jw.ui.tk
Author: Johnny Wezel
Author-email: dev-jay@wezel.name
License: Apache 2
Keywords: UI GUI Tk user interface
Platform: POSIX
Classifier: Development Status :: 3 - Alpha
Classifier: Environment :: X11 Applications
Classifier: Intended Audience :: Developers
Classifier: License :: OSI Approved :: Apache Software License
Classifier: Natural Language :: English
Classifier: Operating System :: POSIX
Classifier: Operating System :: Unix
Classifier: Programming Language :: Python :: 2
Classifier: Programming Language :: Python :: 2.7
